{
  "db_name": "PostgreSQL",
  "query": "\n            SELECT a.id, a.graph_id, a.name, a.mandate_ref, a.persistent,\n                   a.created_at as \"created_at!: chrono::DateTime<chrono::Utc>\"\n            FROM agents a\n            JOIN edges e ON e.child_agent_id = a.id\n            WHERE e.parent_agent_id = $1\n            ORDER BY a.created_at ASC\n            ",
  "describe": {
    "columns": [
      {
        "ordinal": 0,
        "name": "id",
        "type_info": "Uuid"
      },
      {
        "ordinal": 1,
        "name": "graph_id",
        "type_info": "Uuid"
      },
      {
        "ordinal": 2,
        "name": "name",
        "type_info": "Text"
      },
      {
        "ordinal": 3,
        "name": "mandate_ref",
        "type_info": "Text"
      },
      {
        "ordinal": 4,
        "name": "persistent",
        "type_info": "Bool"
      },
      {
        "ordinal": 5,
        "name": "created_at!: chrono::DateTime<chrono::Utc>",
        "type_info": "Timestamptz"
      }
    ],
    "parameters": {
      "Left": [
        "Uuid"
      ]
    },
    "nullable": [
      false,
      false,
      false,
      true,
      false,
      false
    ]
  },
  "hash": "de8fd1aa899e6f7e909bc05ab579a88dc16e732235549ebb0fd9001c18ac21f0"
}
